README
setup.py
spaceapi/__init__.py
spaceapi/download.py
spaceapi.egg-info/PKG-INFO
spaceapi.egg-info/SOURCES.txt
spaceapi.egg-info/dependency_links.txt
spaceapi.egg-info/entry_points.txt
spaceapi.egg-info/pbr.json
spaceapi.egg-info/requires.txt
spaceapi.egg-info/top_level.txt