Metadata-Version: 1.1
Name: spaceapi
Version: 0.1.2
Summary: Download and archive Space API data
Home-page: http://dada.pink/spaceapi
Author: Thomas Levine
Author-email: _@thomaslevine.com
License: AGPL
Platform: UNKNOWN
Classifier: Programming Language :: Python :: 3.4
